ColorStr.py
colors.py
colorstrparser.py
ColorStr-1.3.dist-info/DESCRIPTION.rst
ColorStr-1.3.dist-info/METADATA
ColorStr-1.3.dist-info/RECORD
ColorStr-1.3.dist-info/WHEEL
ColorStr-1.3.dist-info/metadata.json
ColorStr-1.3.dist-info/top_level.txt
