Metadata-Version: 2.0
Name: ColorStr
Version: 1.3
Summary: A better way to output colored text
Home-page: https://github.com/mclt0568/ColorStr
Author: mclt0568
Author-email: tis7bfrankie@gmail.com
License: UNKNOWN
Platform: UNKNOWN
Classifier: Programming Language :: Python :: 3
Classifier: License :: OSI Approved :: Apache Software License
Classifier: Operating System :: OS Independent
